{"key":"iDMk2","title":"document","name":"document","extName":"","path":"/data/document","class":"files-tree-item","slots":{"icon":"fileIcon"},"iconClass":"#icon-yellowFolder","isDir":true,"children":[{"key":"j3FMK","title":"markdown","name":"markdown","extName":"","path":"/data/document/markdown","class":"files-tree-item","slots":{"icon":"fileIcon"},"iconClass":"#icon-yellowFolder","isDir":true,"children":[{"key":"f5Srp","title":"1.md","name":"1.md","extName":".md","path":"/data/document/markdown/1.md","class":"files-tree-item","slots":{"icon":"fileIcon"},"iconClass":"#icon-markdown","isDir":false},{"key":"XSza5","title":"2.md","name":"2.md","extName":".md","path":"/data/document/markdown/2.md","class":"files-tree-item","slots":{"icon":"fileIcon"},"iconClass":"#icon-markdown","isDir":false}]},{"key":"aXiEY","title":"vue","name":"vue","extName":"","path":"/data/document/vue","class":"files-tree-item","slots":{"icon":"fileIcon"},"iconClass":"#icon-yellowFolder","isDir":true,"children":[{"key":"EC8GX","title":"1.vue","name":"1.vue","extName":".vue","path":"/data/document/vue/1.vue","class":"files-tree-item","slots":{"icon":"fileIcon"},"iconClass":"#icon-vue","isDir":false},{"key":"DeG5J","title":"2.vue","name":"2.vue","extName":".vue","path":"/data/document/vue/2.vue","class":"files-tree-item","slots":{"icon":"fileIcon"},"iconClass":"#icon-vue","isDir":false},{"key":"cyBW7","title":"3.vue","name":"3.vue","extName":".vue","path":"/data/document/vue/3.vue","class":"files-tree-item","slots":{"icon":"fileIcon"},"iconClass":"#icon-vue","isDir":false}]}]}